Workbook

Sheet Dashboard
A1: Kenya Population & Economic Analysis (2020–2024)
A3: Population(M),2024 | C3: GDP per capita(Ksh),2024 | E3: Pop growth,5-yr | G3: GDP per capita growth,5-yr | I3: Real income gain
A4: ='Pivot table'!$B$8 -> 52.4 | C4: ='Pivot table'!$B$28 -> 309460.4 | E4: =('Pivot table'!$B$8-'Pivot table'!$B$4)/'Pivot table'!$B$4 -> 0.073770492 | G4: =('Pivot table'!$B$28-'Pivot table'!$B$24)/'Pivot table'!$B$24 -> 0.40989247 | I4: =G4-E4 -> 0.33612198
A5: ="YoY: "&TEXT(('Pivot table'!$B$8-'Pivot table'!$B$7)/'Pivot table'!$B$7,"0.0%") -> YoY: 1.7% | C5: ="YoY: "&TEXT(('Pivot table'!$B$28-'Pivot table'!$B$27)/'Pivot table'!$B$27,"0.0%") -> YoY: 6.1% | E5: 2020-2024 | G5: 2020-2024 | I5: 2020-2024

Sheet Pivot table
A1: indicator_name | B1: population
A3: Row Labels | B3: Population | C3: Growth rate
A4: 2020 | B4: 48.8
A5: 2021 | B5: 49.7 | C5: =(B5-B4)/B4 -> 0.018442623
A6: 2022 | B6: 50.6 | C6: =(B6-B5)/B5 -> 0.018108652
A7: 2023 | B7: 51.5 | C7: =(B7-B6)/B6 -> 0.017786561
A8: 2024 | B8: 52.4 | C8: =(B8-B7)/B7 -> 0.017475728
A9: Grand Total | B9: 253
E17: Population shows steady growth from 48.8M in 2020 to 52.4M in 2024, with consistent year-over-year increases of ~1.8%–2%.
A21: indicator_name | B21: gdp_per_capita
A23: Row Labels | B23: gdp_per_capita | C23: Growth rate
A24: 2020 | B24: 219492.2
A25: 2021 | B25: 241906.8 | C25: =(B25-B24)/B24 -> 0.10212026
A26: 2022 | B26: 266473 | C26: =(B26-B25)/B25 -> 0.10155233
A27: 2023 | B27: 291769.7 | C27: =(B27-B26)/B26 -> 0.094931569
A28: 2024 | B28: 309460.4 | C28: =(B28-B27)/B27 -> 0.06063241
A29: Grand Total | B29: 1329102.1
A37: Year | B37: gdp_per_capita | C37: Population Growth rate | D37: GDP per capita Growth rate
A38: =A24 -> 2020 | B38: =B24 -> 219492.2
A39: =A25 -> 2021 | B39: =B25 -> 241906.8 | C39: =C5 -> 0.018442623 | D39: =C25 -> 0.10212026
A40: =A26 -> 2022 | B40: =B26 -> 266473 | C40: =C6 -> 0.018108652 | D40: =C26 -> 0.10155233
A41: =A27 -> 2023 | B41: =B27 -> 291769.7 | C41: =C7 -> 0.017786561 | D41: =C27 -> 0.094931569
A42: =A28 -> 2024 | B42: =B28 -> 309460.4 | C42: =C8 -> 0.017475728 | D42: =C28 -> 0.06063241

Sheet indicators dataset
A1: id | B1: indicator_name | C1: year | D1: value
A2: 1 | B2: population | C2: 2020 | D2: 48.8
A3: 2 | B3: population | C3: 2021 | D3: 49.7
A4: 4 | B4: gdp_growth | C4: 2020 | D4: -0.3
A5: 5 | B5: population | C5: 2022 | D5: 50.6
A6: 6 | B6: population | C6: 2023 | D6: 51.5
A7: 7 | B7: population | C7: 2024 | D7: 52.4
A8: 8 | B8: gdp_growth | C8: 2021 | D8: 7.6
A9: 9 | B9: gdp_growth | C9: 2022 | D9: 4.9
A10: 12 | B10: trade_balance | C10: 2020 | D10: -999853.9
A11: 13 | B11: gdp_growth | C11: 2023 | D11: 5.7
A12: 14 | B12: gdp_growth | C12: 2024 | D12: 4.7
A13: 15 | B13: trade_balance | C13: 2021 | D13: -1375688
... A81: 88 | B81: education_otherpostsecondary_enrolment | C81: 2024 | D81: 751
